yowasp_silice/__init__.py
yowasp_silice/report_cycles.py
yowasp_silice/silice.wasm
yowasp_silice/silice_make.py
yowasp_silice/share/silice/frameworks/boards/README.md
yowasp_silice/share/silice/frameworks/boards/TROUBLESHOOTING.md
yowasp_silice/share/silice/frameworks/boards/boards.json
yowasp_silice/share/silice/frameworks/boards/bare/bare.sh
yowasp_silice/share/silice/frameworks/boards/bare/bare.v
yowasp_silice/share/silice/frameworks/boards/bare/board.json
yowasp_silice/share/silice/frameworks/boards/brot/board.json
yowasp_silice/share/silice/frameworks/boards/brot/brot.pcf
yowasp_silice/share/silice/frameworks/boards/brot/brot.v
yowasp_silice/share/silice/frameworks/boards/colorlight/board.json
yowasp_silice/share/silice/frameworks/boards/colorlight/colorlight.v
yowasp_silice/share/silice/frameworks/boards/colorlight/colorlight_i9_v7.2.lpf
yowasp_silice/share/silice/frameworks/boards/crosslink_nx_evn/board.json
yowasp_silice/share/silice/frameworks/boards/crosslink_nx_evn/crosslink_nx_evn.pdc
yowasp_silice/share/silice/frameworks/boards/crosslink_nx_evn/crosslink_nx_evn.sh
yowasp_silice/share/silice/frameworks/boards/crosslink_nx_evn/crosslink_nx_evn.v
yowasp_silice/share/silice/frameworks/boards/de10nano/board.json
yowasp_silice/share/silice/frameworks/boards/de10nano/build.sdc
yowasp_silice/share/silice/frameworks/boards/de10nano/de10nano.v
yowasp_silice/share/silice/frameworks/boards/de10nano/pins.tcl
yowasp_silice/share/silice/frameworks/boards/de2/board.json
yowasp_silice/share/silice/frameworks/boards/de2/de2.v
yowasp_silice/share/silice/frameworks/boards/de2/pins.tcl
yowasp_silice/share/silice/frameworks/boards/ecpix5/board.json
yowasp_silice/share/silice/frameworks/boards/ecpix5/ecpix5.lpf
yowasp_silice/share/silice/frameworks/boards/ecpix5/ecpix5.v
yowasp_silice/share/silice/frameworks/boards/fomu/board.json
yowasp_silice/share/silice/frameworks/boards/fomu/fomu-hacker.pcf
yowasp_silice/share/silice/frameworks/boards/fomu/fomu-hacker.sh
yowasp_silice-1.0.post338513.dist-info/METADATA
yowasp_silice-1.0.post338513.dist-info/WHEEL
yowasp_silice-1.0.post338513.dist-info/entry_points.txt
yowasp_silice-1.0.post338513.dist-info/top_level.txt
yowasp_silice-1.0.post338513.dist-info/RECORD
