Metadata-Version: 2.1
Name: yowasp-silice
Version: 1.0.post338513
Summary: Silice HDL
Author-email: sylefeb <sylefeb@antexel.com>, Catherine <whitequark@whitequark.org>
License: ISC
Project-URL: Homepage, https://yowasp.org/
Project-URL: Source Code, https://github.com/sylefeb/silice-yowasp
Project-URL: Bug Tracker, https://github.com/sylefeb/silice-yowasp/issues
Classifier: License :: OSI Approved :: ISC License (ISCL)
Requires-Dist: yowasp-runtime~=1.12
Requires-Dist: importlib-resources; python_version < "3.9"
